cli/__init__.py
cli/db_utils.py
cli/lazy_imports.py
cli/main.py
cli/main_extend.py
cli/utils.py
core/__init__.py
core/agents/sml_agents.py
core/audio.py
core/chat.py
core/chunking_strategies.py
core/config.py
core/cut_audio.py
core/prompt.py
llm_to_cli-0.1.8.dist-info/LICENSE
llm_to_cli-0.1.8.dist-info/METADATA
llm_to_cli-0.1.8.dist-info/WHEEL
llm_to_cli-0.1.8.dist-info/entry_points.txt
llm_to_cli-0.1.8.dist-info/RECORD
