Metadata-Version: 2.3
Name: llm-to-cli
Version: 0.1.8
Summary: simple llm based tools to access from cli
Author: tikendraw
Author-email: tikendraksahu1029@gmail.com
Requires-Python: >=3.11,<4.0
Classifier: Programming Language :: Python :: 3
Classifier: Programming Language :: Python :: 3.11
Classifier: Programming Language :: Python :: 3.12
Classifier: Programming Language :: Python :: 3.13
Provides-Extra: agents
Requires-Dist: click (>=8.1.8,<9.0.0)
Requires-Dist: litellm (>=1.59.9,<2.0.0)
Requires-Dist: rich (>=13.9.4,<14.0.0)
Requires-Dist: smolagents (>=0.1.0) ; extra == "agents"
